COPYING
MANIFEST.in
README.rst
setup.py
outernet_metadata/__init__.py
outernet_metadata/argutil.py
outernet_metadata/custom_validators.py
outernet_metadata/flowutil.py
outernet_metadata/pathutil.py
outernet_metadata/template.py
outernet_metadata/validate.py
outernet_metadata/validator.py
outernet_metadata/values.py
outernet_metadata.egg-info/PKG-INFO
outernet_metadata.egg-info/SOURCES.txt
outernet_metadata.egg-info/dependency_links.txt
outernet_metadata.egg-info/entry_points.txt
outernet_metadata.egg-info/requires.txt
outernet_metadata.egg-info/top_level.txt