Metadata-Version: 1.1
Name: outernet-metadata
Version: 0.8.post1
Summary: Library for working with Outernet metadata
Home-page: https://github.com/Outernet-Project/bottle-fdsend
Author: Outernet Inc
Author-email: apps@outernet.is
License: GPLv3
Keywords: json,validation,templates,metadata,outernet
Platform: UNKNOWN
Classifier: Development Status :: 4 - Beta
Classifier: License :: OSI Approved :: GNU General Public License v3 or later (GPLv3+)
Classifier: Programming Language :: Python :: 3.4
Classifier: Programming Language :: Python :: 2.7
